ipy_modal_backport-0.3.0.dist-info/licenses/LICENSE
modal_backport/__init__.py
modal_backport/components.py
modal_backport/context.py
modal_backport/enums.py
modal_backport/modal.py
ipy_modal_backport-0.3.0.dist-info/METADATA
ipy_modal_backport-0.3.0.dist-info/WHEEL
ipy_modal_backport-0.3.0.dist-info/top_level.txt
ipy_modal_backport-0.3.0.dist-info/RECORD
