Metadata-Version: 2.4
Name: ipy-modal-backport
Version: 0.3.0
Summary: A project to backport new modal features into interactions.py v5.
Home-page: https://github.com/Astrea-Stellarium-Labs/ipy-modal-backport
Author: AstreaTSS
Classifier: Programming Language :: Python :: 3
Classifier: License :: OSI Approved :: MIT License
Classifier: Operating System :: OS Independent
Requires-Python: >=3.10
License-File: LICENSE
Requires-Dist: discord-py-interactions>=5.15.0
Dynamic: author
Dynamic: classifier
Dynamic: description
Dynamic: description-content-type
Dynamic: home-page
Dynamic: license-file
Dynamic: requires-dist
Dynamic: requires-python
Dynamic: summary
